ezpkl/__init__.py
ezpkl/pickling.py
ezpkl/refrigerator.py
ezpkl/texting.py
tests/__init__.py
tests/test_ezpkl.py
tests/test_texting.py
ezpkl-0.2.0.dist-info/LICENSE
ezpkl-0.2.0.dist-info/METADATA
ezpkl-0.2.0.dist-info/WHEEL
ezpkl-0.2.0.dist-info/top_level.txt
ezpkl-0.2.0.dist-info/RECORD
